{
  "shape": "hash",
  "dataset_target_mb": 200.0,
  "dataset_measured_mb": 200.1,
  "n_rules": 1104222,
  "alloc": 100,
  "workers": 2,
  "model": "process_refork",
  "mode": "process",
  "ruby": "ruby 4.0.5 (2026-05-20 revision 64336ffd0e) +PRISM [aarch64-linux]",
  "platform": "aarch64-linux",
  "mem_measured": true,
  "run_class": "reduced",
  "duration_s": 3.0,
  "reps": 3,
  "throughput_items_s": 10329.062899242304,
  "throughput_min_items_s": 9980.22933203293,
  "throughput_max_items_s": 11297.101386086011,
  "pss_kb": 386066,
  "pss_mb": 377.0,
  "pss_lo_mb": 374.8,
  "pss_hi_mb": 377.8,
  "private_dirty_kb": 195788,
  "private_dirty_mb": 191.2,
  "shared_clean_kb": 13804,
  "shared_clean_mb": 13.5,
  "shared_dirty_kb": 560916,
  "shared_dirty_mb": 547.8,
  "rss_kb": 770016,
  "rss_mb": 752.0,
  "correct": true,
  "gc_count": 11,
  "allocated_objects": 7000042,
  "startup_prep_s": 0.2884994429996368,
  "recurring_fork_s": 0.3337339859999702,
  "gens_median": 3,
  "refork_interval_p50_s": 1.1957607659996938,
  "refork_interval_p95_s": 1.302107253000031
}