{
  "shape": "hash",
  "dataset_target_mb": 200.0,
  "dataset_measured_mb": 200.1,
  "n_rules": 1104222,
  "alloc": 0,
  "workers": 2,
  "model": "process_gc_compact_plus_warmup",
  "mode": "process",
  "ruby": "ruby 4.0.5 (2026-05-20 revision 64336ffd0e) +PRISM [aarch64-linux]",
  "platform": "aarch64-linux",
  "mem_measured": true,
  "run_class": "reduced",
  "duration_s": 3.0,
  "reps": 3,
  "throughput_items_s": 13452.239114040565,
  "throughput_min_items_s": 13017.532151590976,
  "throughput_max_items_s": 13458.981397428275,
  "pss_kb": 235302,
  "pss_mb": 229.8,
  "pss_lo_mb": 229.8,
  "pss_hi_mb": 229.8,
  "private_dirty_kb": 44636,
  "private_dirty_mb": 43.6,
  "shared_clean_kb": 13268,
  "shared_clean_mb": 13.0,
  "shared_dirty_kb": 561840,
  "shared_dirty_mb": 548.7,
  "rss_kb": 619740,
  "rss_mb": 605.2,
  "correct": true,
  "gc_count": 0,
  "allocated_objects": 10,
  "startup_prep_s": 0.22394469899973046,
  "recurring_fork_s": 0,
  "gens_median": 1,
  "refork_interval_p50_s": null,
  "refork_interval_p95_s": null
}